face_mask/__init__.py
face_mask/_version.py
face_mask/core/__init__.py
face_mask/core/dataset_generator.py
face_mask/core/face_processor.py
face_mask/core/image_mixer.py
face_mask/core/mask_generator.py
face_mask/utils/__init__.py
face_mask/utils/coco_utils.py
face_mask/utils/display_utils.py
face_mask/utils/image_utils.py
synthetic_face_masks-1.0.0.dist-info/licenses/LICENSE
synthetic_face_masks-1.0.0.dist-info/METADATA
synthetic_face_masks-1.0.0.dist-info/WHEEL
synthetic_face_masks-1.0.0.dist-info/entry_points.txt
synthetic_face_masks-1.0.0.dist-info/top_level.txt
synthetic_face_masks-1.0.0.dist-info/RECORD
