Metadata-Version: 2.4
Name: synthetic-face-masks
Version: 1.0.0
Summary: A Python library for generating synthetic face mask datasets by mixing facial regions
Author-email: Eldho Abraham <eldho.abraham@amadeus.com>
Maintainer-email: Eldho Abraham <eldho.abraham@amadeus.com>
License: MIT
Project-URL: Homepage, https://github.com/AmadeusITGroup/synthetic-face-masks
Project-URL: Repository, https://github.com/AmadeusITGroup/synthetic-face-masks
Project-URL: Bug Tracker, https://github.com/AmadeusITGroup/synthetic-face-masks/issues
Project-URL: Documentation, https://github.com/AmadeusITGroup/synthetic-face-masks/blob/main/README.md
Keywords: face mask,dataset generation,computer vision,machine learning,synthetic face data,face detection,image processing,COCO format,MediaPipe
Classifier: Development Status :: 4 - Beta
Classifier: Intended Audience :: Science/Research
Classifier: Intended Audience :: Developers
Classifier: Topic :: Scientific/Engineering :: Artificial Intelligence
Classifier: Topic :: Scientific/Engineering :: Image Processing
Classifier: Topic :: Software Development :: Libraries :: Python Modules
Classifier: Programming Language :: Python :: 3
Classifier: Programming Language :: Python :: 3.7
Classifier: Programming Language :: Python :: 3.8
Classifier: Programming Language :: Python :: 3.9
Classifier: Programming Language :: Python :: 3.10
Classifier: Programming Language :: Python :: 3.11
Classifier: Programming Language :: Python :: 3.12
Classifier: Operating System :: OS Independent
Requires-Python: >=3.7
License-File: LICENSE
Requires-Dist: opencv-python>=4.8.0
Requires-Dist: mediapipe>=0.9.1.0
Requires-Dist: numpy>=1.21.0
Requires-Dist: imgaug>=0.4.0
Requires-Dist: tqdm>=4.64.0
Requires-Dist: Pillow>=8.0.0
Provides-Extra: dev
Requires-Dist: pytest>=6.0; extra == "dev"
Requires-Dist: pytest-cov>=2.0; extra == "dev"
Requires-Dist: black>=21.0; extra == "dev"
Requires-Dist: flake8>=3.8; extra == "dev"
Requires-Dist: isort>=5.0; extra == "dev"
Requires-Dist: mypy>=0.900; extra == "dev"
Provides-Extra: docs
Requires-Dist: sphinx>=4.0; extra == "docs"
Requires-Dist: sphinx-rtd-theme>=1.0; extra == "docs"
Requires-Dist: myst-parser>=0.15; extra == "docs"
Dynamic: license-file
